numerus/__init__.py
numerus/checks.py
numerus/geometry.py
numerus-0.1.0.dist-info/DESCRIPTION.rst
numerus-0.1.0.dist-info/METADATA
numerus-0.1.0.dist-info/RECORD
numerus-0.1.0.dist-info/WHEEL
numerus-0.1.0.dist-info/metadata.json
numerus-0.1.0.dist-info/top_level.txt
